stackl_client/__init__.py
stackl_client/api_client.py
stackl_client/configuration.py
stackl_client/exceptions.py
stackl_client/rest.py
stackl_client/api/__init__.py
stackl_client/api/about_api.py
stackl_client/api/configurator_api.py
stackl_client/api/documents_api.py
stackl_client/api/functional_requirements_api.py
stackl_client/api/policies_api.py
stackl_client/api/policy_agent_api.py
stackl_client/api/policy_templates_api.py
stackl_client/api/services_api.py
stackl_client/api/stack_application_templates_api.py
stackl_client/api/stack_infrastructure_templates_api.py
stackl_client/api/stack_instances_api.py
stackl_client/api/terraform_api.py
stackl_client/models/__init__.py
stackl_client/models/base_document.py
stackl_client/models/collection_document.py
stackl_client/models/connection_credentials.py
stackl_client/models/functional_requirement.py
stackl_client/models/functional_requirement_status.py
stackl_client/models/http_validation_error.py
stackl_client/models/infrastructure_base_document.py
stackl_client/models/infrastructure_target.py
stackl_client/models/invocation.py
stackl_client/models/policy.py
stackl_client/models/policy_template.py
stackl_client/models/service.py
stackl_client/models/stack_application_template.py
stackl_client/models/stack_infrastructure_template.py
stackl_client/models/stack_instance.py
stackl_client/models/stack_instance_invocation.py
stackl_client/models/stack_instance_service.py
stackl_client/models/stack_instance_status.py
stackl_client/models/stack_instance_update.py
stackl_client/models/validation_error.py
stackl_client-0.1.0.dist-info/METADATA
stackl_client-0.1.0.dist-info/WHEEL
stackl_client-0.1.0.dist-info/top_level.txt
stackl_client-0.1.0.dist-info/RECORD
